jupino/__init__.py
jupino/anno_session.py
jupino/interface.py
jupino/widgets/__init__.py
jupino/widgets/defaults.py
jupino/widgets/labels.py
jupino/widgets/utils.py
jupino/widgets/x.py
jupino-0.1.0.dist-info/LICENSE
jupino-0.1.0.dist-info/WHEEL
jupino-0.1.0.dist-info/METADATA
jupino-0.1.0.dist-info/RECORD
