Metadata-Version: 2.1
Name: jupino
Version: 0.1.0
Summary: Annotate data using Jupyter notebook
License: MIT
Author: Sanjaya Subedi
Author-email: jangedoo@gmail.com
Requires-Python: >=3.8,<4.0
Classifier: License :: OSI Approved :: MIT License
Classifier: Programming Language :: Python :: 3
Classifier: Programming Language :: Python :: 3.8
Classifier: Programming Language :: Python :: 3.9
Requires-Dist: jupyter (>=1.0.0,<2.0.0)
